cepa-1.8.4.data/scripts/tor-prompt
stem/__init__.py
stem/cached_fallbacks.cfg
stem/cached_manual.sqlite
stem/connection.py
stem/control.py
stem/directory.py
stem/exit_policy.py
stem/manual.py
stem/prereq.py
stem/process.py
stem/settings.cfg
stem/socket.py
stem/version.py
stem/client/__init__.py
stem/client/cell.py
stem/client/datatype.py
stem/descriptor/__init__.py
stem/descriptor/bandwidth_file.py
stem/descriptor/certificate.py
stem/descriptor/collector.py
stem/descriptor/export.py
stem/descriptor/extrainfo_descriptor.py
stem/descriptor/hidden_service.py
stem/descriptor/hidden_service_descriptor.py
stem/descriptor/microdescriptor.py
stem/descriptor/networkstatus.py
stem/descriptor/reader.py
stem/descriptor/remote.py
stem/descriptor/router_status_entry.py
stem/descriptor/server_descriptor.py
stem/descriptor/tordnsel.py
stem/interpreter/__init__.py
stem/interpreter/arguments.py
stem/interpreter/autocomplete.py
stem/interpreter/commands.py
stem/interpreter/help.py
stem/interpreter/settings.cfg
stem/response/__init__.py
stem/response/add_onion.py
stem/response/authchallenge.py
stem/response/events.py
stem/response/getconf.py
stem/response/getinfo.py
stem/response/mapaddress.py
stem/response/protocolinfo.py
stem/util/__init__.py
stem/util/conf.py
stem/util/connection.py
stem/util/ed25519.py
stem/util/enum.py
stem/util/log.py
stem/util/lru_cache.py
stem/util/ordereddict.py
stem/util/ports.cfg
stem/util/proc.py
stem/util/str_tools.py
stem/util/system.py
stem/util/term.py
stem/util/test_tools.py
stem/util/tor_tools.py
cepa-1.8.4.dist-info/LICENSE
cepa-1.8.4.dist-info/METADATA
cepa-1.8.4.dist-info/WHEEL
cepa-1.8.4.dist-info/top_level.txt
cepa-1.8.4.dist-info/RECORD
