Metadata-Version: 2.1
Name: cepa
Version: 1.8.4
Summary: Stem is a Python controller library that allows applications to interact with Tor (https://www.torproject.org/).
Home-page: https://stem.torproject.org/
Author: Damian Johnson
Author-email: atagar@torproject.org
License: LGPLv3
Keywords: tor onion controller
Classifier: Development Status :: 5 - Production/Stable
Classifier: Intended Audience :: Developers
Classifier: License :: OSI Approved :: GNU Lesser General Public License v3 (LGPLv3)
Classifier: Topic :: Security
Classifier: Topic :: Software Development :: Libraries :: Python Modules
License-File: LICENSE
Requires-Dist: setuptools (>=65.4.1)
